{
  "success": true,
  "message": "success",
  "code": 200,
  "timestamp": 1573005786772,
  "result": {
    "content": [{
      "id": "202152591826620555",
      "createBy": "admin",
      "createTime": "2019-10-31 10:14:35",
      "updateBy": null,
      "updateTime": "2019-10-31 10:15:08",
      "delFlag": 0,
      "appName": "brapm-grpc-java-application",
      "appId": 0,
      "emailRemark": "yzlTongbi",
      "endTime": "2019-10-01T16:00:00.000+0000",
      "startTime": "2019-10-01T04:00:00.000+0000",
      "level": 3,
      "projectName": "brapm-grpc-java-project",
      "projectId": 3898,
      "provideType": 0,
      "ruleName": "yzlZTongbi",
      "interfaceName": "同比告警无服务",
      "fuWu": null,
      "alertsStatus": 1,
      "alertType": 2,
      "noticeWay": 0,
      "sameCompareType": 1,
      "sameCompareGra": 0,
      "sameCompareRule": 1,
      "alertRuleDescriptionsList": [{
        "id": "202152591839203666",
        "createBy": null,
        "createTime": null,
        "updateBy": null,
        "updateTime": null,
        "delFlag": 0,
        "description": 13,
        "condition": 1,
        "unit": 10,
        "unitEnum": 2,
        "moreThanMinute": null,
        "conditionDetail": "大于",
        "unitEnumDetail": "百分比",
        "descriptionDeatil": "平均响应时间",
        "descInfo": "交易日平均响应时间天同比(时间粒度: 1分钟)大于10百分比告警。",
        "sameCompareType": 1,
        "sameCompareGra": 0,
        "sameCompareRule": 1,
        "moreThanSecond": null,
        "moreThanUnit": null,
        "sameCompareTypeDeatil": "天同比",
        "sameCompareGraDeatil": "1分钟",
        "sameCompareRuleDeatil": "交易日",
        "moreThanUnitDeatil": null,
        "talertsId": "202152591826620555"
      }],
      "alertUserObjectList": [{
        "id": "682265633886208",
        "createBy": "",
        "createTime": "2018-05-01 16:13:51",
        "updateBy": "",
        "updateTime": "2018-12-10 09:50:59",
        "delFlag": 0,
        "username": "admin",
        "password": "$2a$10$LPNcntYGxcWSngwZJj08D.A2biv.k2sQUsGrxLc2HkvL9DA1LbLaO",
        "nickName": null,
        "mobile": "18362218906",
        "email": "32345435@qq.com",
        "address": "[\"510000\",\"510100\",\"510104\"]",
        "sex": 1,
        "avatar": "http://p77xsahe9.bkt.clouddn.com/788eb3e78206429eb34fc7cd3e1e46f4.jpg",
        "type": 1,
        "status": 0,
        "description": "{\"datasurvey\":{\"queryServeTop10\":{\"badly\":1500,\"warn\":500,\"general\":0},\"queryErrorTop10\":{\"badly\":1500,\"warn\":500,\"general\":0}}}",
        "roles": [{
          "id": "496138616573952",
          "createBy": null,
          "createTime": null,
          "updateBy": null,
          "updateTime": null,
          "delFlag": 0,
          "name": "ROLE_MANAGE_ADMIN",
          "defaultRole": null,
          "permissions": null,
          "canShow": true
        }],
        "permissions": [{
          "id": "67002981710565376",
          "createBy": null,
          "createTime": null,
          "updateBy": null,
          "updateTime": null,
          "delFlag": 0,
          "name": null,
          "level": 3,
          "type": 1,
          "title": "删除告警",
          "path": "/api/alert/deleteAlert",
          "component": null,
          "icon": null,
          "buttonType": "delete",
          "parentId": "67000546510245888",
          "description": null,
          "sortOrder": 1,
          "status": 0,
          "children": null,
          "permTypes": null,
          "expand": true,
          "checked": false,
          "selected": false,
          "projectName": null,
          "projectId": null,
          "owner": null
        }],
        "groups": null,
        "groupId": null,
        "groupName": null,
        "employeeNumber": "BN00249"
      }],
      "startTimeString": "2019-10-01 12:00:00",
      "endTimeString": "2019-10-02 00:00:00",
      "startOrEnd": 0,
      "userObjectList": null
    }],
    "pageable": {
      "sort": {
        "sorted": true,
        "unsorted": false
      },
      "offset": 0,
      "pageSize": 6,
      "pageNumber": 0,
      "unpaged": false,
      "paged": true
    },
    "totalElements": 1,
    "last": true,
    "totalPages": 1,
    "number": 0,
    "size": 6,
    "sort": {
      "sorted": true,
      "unsorted": false
    },
    "numberOfElements": 1,
    "first": true
  }
}
